dropfix/__init__.py
dropfix/_checker.py
dropfix/_formatter.py
dropfix/_logger.py
dropfix/dropfix.py
dropfix-0.2.1.dist-info/WHEEL
dropfix-0.2.1.dist-info/entry_points.txt
dropfix-0.2.1.dist-info/METADATA
dropfix-0.2.1.dist-info/RECORD
