Metadata-Version: 2.3
Name: dropfix
Version: 0.2.1
Summary: dropfix helps you configure Dropbox to ignore specific development directories (`.venv`, `.conda`, `node_modules`) that don't need to be synced across machines.
Keywords: python
Author: Shane Holloman
Author-email: Shane Holloman <shaneholloman@gmail.com>
Classifier: Intended Audience :: Developers
Classifier: Programming Language :: Python
Classifier: Programming Language :: Python :: 3
Classifier: Programming Language :: Python :: 3.10
Classifier: Programming Language :: Python :: 3.11
Classifier: Programming Language :: Python :: 3.12
Classifier: Programming Language :: Python :: 3.13
Classifier: Topic :: Software Development :: Libraries :: Python Modules
Requires-Dist: rich
Requires-Python: >=3.10, <4.0
Project-URL: Documentation, https://shaneholloman.github.io/dropfix/
Project-URL: Homepage, https://shaneholloman.github.io/dropfix/
Project-URL: Repository, https://github.com/shaneholloman/dropfix
